tests/__init__.py
tests/test_env.py
tests/test_markdown.py
tests/stdlib/__init__.py
tests/stdlib/test_builtin.py
tests/stdlib/test_sci.py
tests/stdlib/test_str.py
tests/stdlib/unit/__init__.py
tests/stdlib/unit/test_temp.py
zcalc/__init__.py
zcalc/__main__.py
zcalc/cmd.py
zcalc/env.py
zcalc/lib.py
zcalc/stdlib/__init__.py
zcalc/stdlib/bit.py
zcalc/stdlib/builtin.py
zcalc/stdlib/math.py
zcalc/stdlib/sci.py
zcalc/stdlib/str.py
zcalc/stdlib/unit/__init__.py
zcalc/stdlib/unit/si.py
zcalc/stdlib/unit/temp.py
zcalc-0.4.0.dist-info/LICENSE
zcalc-0.4.0.dist-info/METADATA
zcalc-0.4.0.dist-info/WHEEL
zcalc-0.4.0.dist-info/entry_points.txt
zcalc-0.4.0.dist-info/top_level.txt
zcalc-0.4.0.dist-info/RECORD
