Metadata-Version: 2.1
Name: zcalc
Version: 0.4.0
Summary: A fun RPN calculator
Home-page: https://github.com/blackchip-org/zcalc
Author: Mike McGann
Author-email: mike.mcgann@blackchip.org
License: UNKNOWN
Project-URL: Bug Tracker, https://github.com/blackchip-org/zcalc/issues
Platform: UNKNOWN
Classifier: Programming Language :: Python :: 3
Classifier: License :: OSI Approved :: MIT License
Classifier: Operating System :: OS Independent
Requires-Python: >=3.6
License-File: LICENSE
Requires-Dist: pygtrie
Requires-Dist: pyreadline
